shortener/__init__.py
shortener/admin.py
shortener/apps.py
shortener/manager.py
shortener/models.py
shortener/urls.py
shortener/views.py
shortener/migrations/0001_initial.py
shortener/migrations/0002_auto_20181028_1719.py
shortener/migrations/__init__.py
shortener-0.2.1.dist-info/LICENSE
shortener-0.2.1.dist-info/METADATA
shortener-0.2.1.dist-info/WHEEL
shortener-0.2.1.dist-info/top_level.txt
shortener-0.2.1.dist-info/RECORD
