Metadata-Version: 2.1
Name: shortener
Version: 0.2.1
Summary: URL shortener in django
Home-page: https://github.com/pennlabs/shortener
Author: Penn Labs
Author-email: admin@pennlabs.org
License: MIT
Project-URL: Changelog, https://github.com/pennlabs/shortener/blob/master/CHANGELOG.md
Platform: UNKNOWN
Classifier: Framework :: Django
Classifier: Programming Language :: Python
Classifier: Programming Language :: Python :: 3.5
Classifier: Programming Language :: Python :: 3.6
Classifier: Programming Language :: Python :: 3.7
Requires-Python: >=3.5
